scraperator/__init__.py
scraperator/base_scraper.py
scraperator/browser_installer.py
scraperator/markdown_converter.py
scraperator/playwright_scraper.py
scraperator/request_scraper.py
scraperator/scraper.py
scraperator-0.0.5.dist-info/METADATA
scraperator-0.0.5.dist-info/WHEEL
scraperator-0.0.5.dist-info/top_level.txt
scraperator-0.0.5.dist-info/RECORD
