Metadata-Version: 2.2
Name: scraperator
Version: 0.0.5
Summary: A flexible web scraping toolkit with caching capabilities
Author-email: Arved Klöhn <arved.kloehn@gmail.com>
License: MIT
Project-URL: homepage, https://github.com/Redundando/scraperator
Project-URL: repository, https://github.com/Redundando/scraperator
Project-URL: documentation, https://github.com/Redundando/scraperator#readme
Classifier: Development Status :: 4 - Beta
Classifier: Intended Audience :: Developers
Classifier: License :: OSI Approved :: MIT License
Classifier: Programming Language :: Python :: 3
Classifier: Programming Language :: Python :: 3.7
Classifier: Programming Language :: Python :: 3.8
Classifier: Programming Language :: Python :: 3.9
Classifier: Programming Language :: Python :: 3.10
Classifier: Topic :: Internet :: WWW/HTTP
Classifier: Topic :: Software Development :: Libraries :: Python Modules
Requires-Python: >=3.7
Requires-Dist: requests>=2.25.0
Requires-Dist: beautifulsoup4>=4.9.0
Requires-Dist: playwright>=1.20.0
Requires-Dist: python-slugify>=5.0.0
Requires-Dist: cacherator>=0.0.8
Provides-Extra: dev
Requires-Dist: pytest>=6.0.0; extra == "dev"
Requires-Dist: black>=21.5b2; extra == "dev"
Requires-Dist: isort>=5.9.1; extra == "dev"
Requires-Dist: mypy>=0.900; extra == "dev"
Requires-Dist: twine>=3.4.1; extra == "dev"
